WeiXueyuanCJiaocheng/README.md
WeiXueyuanCJiaocheng/__init__.py
WeiXueyuanCJiaocheng/__main__.py
WeiXueyuanCJiaocheng/file.epub
WeiXueyuanCJiaocheng/index.html
WeiXueyuanCJiaocheng/css/__init__.py
WeiXueyuanCJiaocheng/css/annotations.css
WeiXueyuanCJiaocheng/css/main.css
WeiXueyuanCJiaocheng/css/normalize.css
WeiXueyuanCJiaocheng/css/popup.css
WeiXueyuanCJiaocheng/font/__init__.py
WeiXueyuanCJiaocheng/font/fontello.eot
WeiXueyuanCJiaocheng/font/fontello.svg
WeiXueyuanCJiaocheng/font/fontello.ttf
WeiXueyuanCJiaocheng/font/fontello.woff
WeiXueyuanCJiaocheng/img/__init__.py
WeiXueyuanCJiaocheng/img/annotator-glyph-sprite.png
WeiXueyuanCJiaocheng/img/annotator-icon-sprite.png
WeiXueyuanCJiaocheng/img/apple-touch-icon.png
WeiXueyuanCJiaocheng/img/cancelfullscreen.png
WeiXueyuanCJiaocheng/img/close.png
WeiXueyuanCJiaocheng/img/fullscreen.png
WeiXueyuanCJiaocheng/img/loader.gif
WeiXueyuanCJiaocheng/img/menu-icon.png
WeiXueyuanCJiaocheng/img/save.png
WeiXueyuanCJiaocheng/img/saved.png
WeiXueyuanCJiaocheng/img/settings-s.png
WeiXueyuanCJiaocheng/img/settings.png
WeiXueyuanCJiaocheng/img/star.png
WeiXueyuanCJiaocheng/js/__init__.py
WeiXueyuanCJiaocheng/js/epub.js
WeiXueyuanCJiaocheng/js/epub.min.js
WeiXueyuanCJiaocheng/js/epub.min.map
WeiXueyuanCJiaocheng/js/hooks.min.js
WeiXueyuanCJiaocheng/js/hooks.min.map
WeiXueyuanCJiaocheng/js/reader.js
WeiXueyuanCJiaocheng/js/reader.js.map
WeiXueyuanCJiaocheng/js/reader.min.js
WeiXueyuanCJiaocheng/js/reader.min.map
WeiXueyuanCJiaocheng/js/hooks/__init__.py
WeiXueyuanCJiaocheng/js/hooks/extensions/__init__.py
WeiXueyuanCJiaocheng/js/hooks/extensions/highlight.js
WeiXueyuanCJiaocheng/js/libs/__init__.py
WeiXueyuanCJiaocheng/js/libs/jquery.min.js
WeiXueyuanCJiaocheng/js/libs/localforage.min.js
WeiXueyuanCJiaocheng/js/libs/screenfull.js
WeiXueyuanCJiaocheng/js/libs/screenfull.min.js
WeiXueyuanCJiaocheng/js/libs/zip.min.js
WeiXueyuanCJiaocheng/js/plugins/__init__.py
WeiXueyuanCJiaocheng/js/plugins/hypothesis.js
wei_xueyuan_c_jiaocheng-2024.3.2.0.dist-info/METADATA
wei_xueyuan_c_jiaocheng-2024.3.2.0.dist-info/WHEEL
wei_xueyuan_c_jiaocheng-2024.3.2.0.dist-info/entry_points.txt
wei_xueyuan_c_jiaocheng-2024.3.2.0.dist-info/top_level.txt
wei_xueyuan_c_jiaocheng-2024.3.2.0.dist-info/RECORD
